{
  "project_info": {
    "project_number": "309100222597",
    "project_id": "tabib-2bc4a",
    "storage_bucket": "tabib-2bc4a.firebasestorage.app"
  },
  "client": [
    {
      "client_info": {
        "mobilesdk_app_id": "1:309100222597:android:2d873bd1692b3621c5b1ec",
        "android_client_info": {
          "package_name": "com.example.tabib"
        }
      },
      "oauth_client": [],
      "api_key": [
        {
          "current_key": "AIzaSyBsineKK4ObBb8ebHOTL1RcfJttBBfZ5Fk"
        }
      ],
      "services": {
        "appinvite_service": {
          "other_platform_oauth_client": []
        }
      }
    }
  ],
  "configuration_version": "1"
}